LICENSE
MANIFEST.in
README.md
setup.py
zimuzu/__init__.py
zimuzu/cli.py
zimuzu/zumuzu_tv.py
zimuzu.egg-info/PKG-INFO
zimuzu.egg-info/SOURCES.txt
zimuzu.egg-info/dependency_links.txt
zimuzu.egg-info/entry_points.txt
zimuzu.egg-info/requires.txt
zimuzu.egg-info/top_level.txt