Metadata-Version: 1.1
Name: zimuzu
Version: 0.1.0
Summary: Do sign for ZIMUZU: http://www.zimuzu.tv
Home-page: https://github.com/lord63/zimuzu
Author: lord63
Author-email: lord63.j@gmail.com
License: MIT
Keywords: zimuzu sign
Platform: UNKNOWN
Classifier: Development Status :: 4 - Beta
Classifier: Operating System :: POSIX
Classifier: Operating System :: POSIX :: Linux
Classifier: License :: OSI Approved :: MIT License
Classifier: Programming Language :: Python :: 2
Classifier: Programming Language :: Python :: 2.7
